winacl/__init__.py
winacl/_version.py
winacl/dtyp/__init__.py
winacl/dtyp/ace.py
winacl/dtyp/acl.py
winacl/dtyp/guid.py
winacl/dtyp/security_descriptor.py
winacl/dtyp/sid.py
winacl/dtyp/wcee/__init__.py
winacl/dtyp/wcee/backupkey.py
winacl/dtyp/wcee/cryptoapikey.py
winacl/dtyp/wcee/ecdhprivkey.py
winacl/dtyp/wcee/pvkfile.py
winacl/dtyp/wcee/rsaprivkey.py
winacl/examples/__init__.py
winacl/examples/serviceacl.py
winacl/examples/userinfo.py
winacl/functions/__init__.py
winacl/functions/advapi32.py
winacl/functions/constants.py
winacl/functions/defines.py
winacl/functions/dnsapi.py
winacl/functions/highlevel.py
winacl/functions/kernel32.py
winacl/functions/membuff.py
winacl/functions/netapi32.py
winacl/functions/rights_calc.py
winacl/functions/winregistry.py
winacl-0.1.9.dist-info/LICENSE
winacl-0.1.9.dist-info/METADATA
winacl-0.1.9.dist-info/WHEEL
winacl-0.1.9.dist-info/top_level.txt
winacl-0.1.9.dist-info/zip-safe
winacl-0.1.9.dist-info/RECORD
