Metadata-Version: 2.1
Name: winacl
Version: 0.1.9
Summary: ACL/ACE/Security Descriptor manipulation library in pure Python
Home-page: https://github.com/skelsec/winacl
Author: Tamas Jos
Author-email: info@skelsecprojects.com
Classifier: Programming Language :: Python :: 3.6
Classifier: License :: OSI Approved :: MIT License
Classifier: Operating System :: OS Independent
Requires-Python: >=3.6
License-File: LICENSE
Requires-Dist: cryptography>=38.0.1
